{
  "Actor": {
    "types": [
      "pc",
      "npc"
    ],
    "pc": {
      "description": "",
      "languages": "",
      "goal": "",
      "level": 1,
      "xp": 0,
      "hp": {
        "current": 0,
        "bonus": 0
      },
      "attributes": {
        "str": {
          "score": 10
        },
        "dex": {
          "score": 10
        },
        "con": {
          "score": 10
        },
        "int": {
          "score": 10
        },
        "wis": {
          "score": 10
        },
        "cha": {
          "score": 10
        }
      },
      "saves": {
        "hardiness": {
          "bonus": 0
        },
        "evasion": {
          "bonus": 0
        },
        "spirit": {
          "bonus": 0
        }
      },
      "toHitBonus": 1,
      "facts": "",
      "armor": {
        "type": "none",
        "shield": false,
        "bonus": 0,
        "desc": "None (Skin or Clothing)",
        "attribute": "dex",
        "penalizeHardiness": false,
        "penalizeEvasion": false,
        "penalizeSpirit": false
      },
      "effort": {
        "total": 0,
        "atWill": 0,
        "scene": 0,
        "day": 0
      },
      "influence": {
        "total": 0,
        "contributed": 0
      },
      "dominion": {
        "total": 0,
        "contributed": 0,
        "otherIncome": 0
      },
      "wealth": {
        "total": 0,
        "description": ""
      },
      "notes": ""
    },
    "npc": {
      "description": "",
      "goal": "",
      "move": 30,
      "save": 15,
      "morale": 9,
      "ac": 10,
      "hd": {
        "current": 0,
        "max": 0
      },
      "numActions": 1,
      "numAttacks": 1,
      "toHitBonus": 0,
      "effort": {
        "total": 0,
        "atWill": 0,
        "scene": 0,
        "day": 0
      },
      "notes": ""
    }
  },
  "Item": {
    "types": [
      "autoHitAttack",
      "multiDieDamageRoll",
      "attack",
      "project",
      "item",
      "boundWord",
      "divineGift",
      "divineMiracle",
      "artifact",
      "artifactPower",
      "treasure",
      "invocation",
      "tactic",
      "cult"
    ],
    "autoHitAttack": {
      "damageRoll": "1d8",
      "damageBonus": 0,
      "magic": false
    },
    "multiDieDamageRoll": {
      "damageRoll": "1d8",
      "damageBonus": 0
    },
    "attack": {
      "attr": "str",
      "hitBonus": 0,
      "range": "Melee / 30ft",
      "area": "Single Target",
      "damageRoll": "1d8",
      "damageBonus": 0,
      "magic": false
    },
    "item": {
      "description": ""
    },
    "boundWord": {
      "description": ""
    },
    "divineGift": {
      "word": "",
      "description": "",
      "constant": false,
      "instant": false,
      "onTurn": false,
      "action": false,
      "smite": false,
      "noEffort": false,
      "atWill": false,
      "scene": false,
      "day": false,
      "greater": false,
      "combatPower": false
    },
    "artifactPower": {
      "description": "",
      "constant": false,
      "instant": false,
      "onTurn": false,
      "action": false,
      "smite": false,
      "noEffort": false,
      "atWill": false,
      "scene": false,
      "day": false,
      "greater": false,
      "combatPower": false,
      "artifactId": "",
      "effortCost": 1
    },
    "divineMiracle": {
      "description": "",
      "effortCost": 1,
      "smite": false,
      "instant": false,
      "onTurn": false,
      "action": false,
      "day": true,
      "combatPower": false
    },
    "project": {
      "description": "",
      "deeds": "",
      "difficulty": 1,
      "scope": 1,
      "resistance": 0,
      "completed": false,
      "active": false,
      "committedDominion": 0,
      "committedInfluence": 0,
      "contributedDominion": 0,
      "contributedInfluence": 0
    },
    "artifact": {
      "description": "",
      "dominionCost": 0,
      "committedDominion": 0,
      "contributedDominion": 0,
      "completed": false,
      "effort": {
        "total": 0,
        "atWill": 0,
        "scene": 0,
        "day": 0
      },
      "bound": false,
      "mortalEffect": ""
    },
    "treasure": {
      "description": "",
      "value": 0
    },
    "invocation": {
      "description": "",
      "level": ""
    },
    "tactic": {
      "description": ""
    },
    "cult": {
      "description": "",
      "power": 1,
      "cohesion": 1,
      "income": 1,
      "tenets": "",
      "features": "",
      "problems": "",
      "trouble": 0
    }
  }
}
